<T3DataStructure>
	<meta>
		<langDisable>1</langDisable>
	</meta>
	<sheets>
		<sDEF>
			<ROOT>
                <sheetTitle>LLL:EXT:eahstellenticket/Resources/Private/Language/locallang_be.xlf:flexform.tab.setting</sheetTitle>
				<type>array</type>
				<el>
					<settings.Url>
                        <exclude>1</exclude>
                        <label>LLL:EXT:eahstellenticket/Resources/Private/Language/locallang_be.xlf:flexform.url</label>
                        <config>
                            <type>input</type>
                            <size>100</size>
                            <max>400</max>
                            <default></default>
                        </config>
					</settings.Url>

					<!-- enable showeahjprof -->
					<settings.showeahjprof>
                        <exclude>1</exclude>
                        <label>LLL:EXT:eahstellenticket/Resources/Private/Language/locallang_be.xlf:flexform.show.eahj_prof</label>
                        <config>
                            <type>check</type>
                            <default>1</default>
                        </config>
					</settings.showeahjprof>

					<!-- enable showeahjwiss -->
					<settings.showeahjwiss>
                        <exclude>1</exclude>
                        <label>LLL:EXT:eahstellenticket/Resources/Private/Language/locallang_be.xlf:flexform.show.eahj_wiss</label>
                        <config>
                            <type>check</type>
                            <default>1</default>
                        </config>
					</settings.showeahjwiss>

					<!-- enable showeahjverw -->
					<settings.showeahjverw>
                        <exclude>1</exclude>
                        <label>LLL:EXT:eahstellenticket/Resources/Private/Language/locallang_be.xlf:flexform.show.eahj_verwalt</label>
                        <config>
                            <type>check</type>
                            <default>1</default>
                        </config>
					</settings.showeahjverw>

					<!-- enable showeahjausb -->
					<settings.showeahjausb>
                        <exclude>1</exclude>
                        <label>LLL:EXT:eahstellenticket/Resources/Private/Language/locallang_be.xlf:flexform.show.eahj_ausb</label>
                        <config>
                            <type>check</type>
                            <default>1</default>
                        </config>
					</settings.showeahjausb>
				</el>
			</ROOT>
		</sDEF>
		<!--
		################################
			SHEET Template
		################################
		-->
		<template>
			<ROOT>
                <sheetTitle>LLL:EXT:eahstellenticket/Resources/Private/Language/locallang_be.xlf:flexform.tab.template</sheetTitle>
				<type>array</type>
				<el>

					<!-- Template Layout - List -->
					<settings.templateLayoutList>
                        <exclude>1</exclude>
                        <label>LLL:EXT:eahstellenticket/Resources/Private/Language/locallang_be.xlf:flexforms_template.selectlayout_list</label>
                        <config>
                            <type>select</type>
                            <renderType>selectSingle</renderType>
                            <items type="array">
                                <numIndex index="1" type="array">
                                    <numIndex index="0">LLL:EXT:eahstellenticket/Resources/Private/Language/locallang_be.xlf:flexforms_template.selectlayout_list.style1</numIndex>
                                    <numIndex index="1">1</numIndex>
                                </numIndex>
                                <numIndex index="2" type="array">
                                    <numIndex index="0">LLL:EXT:eahstellenticket/Resources/Private/Language/locallang_be.xlf:flexforms_template.selectlayout_list.style2</numIndex>
                                    <numIndex index="1">2</numIndex>
                                </numIndex>
                            </items>
                        </config>
					</settings.templateLayoutList>

				</el>
			</ROOT>
		</template>
	</sheets>
</T3DataStructure>
